deep_crf-1.5.2.dist-info/METADATA
deep_crf-1.5.2.dist-info/RECORD
deep_crf-1.5.2.dist-info/WHEEL
deep_crf-1.5.2.dist-info/entry_points.txt
deep_crf-1.5.2.dist-info/top_level.txt
deepcrf/__init__.py
deepcrf/config.py
deepcrf/deepcrf_eval.py
deepcrf/deepcrf_learn.py
deepcrf/deepcrf_save.py
deepcrf/deevcrf_save.py
deepcrf/default_custom.py
deepcrf/model.py
deepcrf/train.py
deepcrf/transform.py
deepcrf/utils.py
