Metadata-Version: 2.1
Name: deep-crf
Version: 1.5.2
Summary: Sequence label tool base on Bi-LSTM-CRF mode.
Home-page: UNKNOWN
Author: wangsihong
Author-email: wangsihong@live.com
License: GPLv3
Keywords: lstm-crf,crf
Platform: any
Classifier: Development Status :: 4 - Beta
Classifier: Operating System :: OS Independent
Classifier: Intended Audience :: Developers
Classifier: License :: OSI Approved :: BSD License
Classifier: Programming Language :: Python
Classifier: Programming Language :: Python :: Implementation
Classifier: Programming Language :: Python :: 2
Classifier: Programming Language :: Python :: 2.7
Classifier: Programming Language :: Python :: 3
Classifier: Programming Language :: Python :: 3.4
Classifier: Programming Language :: Python :: 3.5
Classifier: Programming Language :: Python :: 3.6
Classifier: Topic :: Software Development :: Libraries
